{"indicator_id":343,"guid":"PUDH:INDI:CfP02","is_cuantitative":true,"dataset_id":"PUDH:INDI:","institution_code":"PUDH","research_code":"INDI","right_name":"Derechos Culturales","right_key":"C","right_name_short":"Culturales","category_id":2,"indicator_category_name":"Contexto financiero y presupuestal","indicator_category_key":"f","indicator_type":"De Proceso","indicator_type_short":"Proceso","indicator_type_code":"P","indicator_code":"CfP02","indicator_sequence":"060206202","indicator_name":"Porcentaje del gasto público federal en ciencia, tecnología e innovación, respecto al gasto nacional en la materia","indicator_definition":"Porcentaje del gasto público federal en ciencia, tecnología e innovación, respecto al gasto nacional en ciencia, tecnología e innovación (público, privado y de instituciones de educación superior).\nEl gasto en ciencia, tecnología e innovación incluye:\n - Gasto en investigación y desarrollo experimental\n - Gasto en posgrado\n - Gasto en servicios de ciencia y tecnología\n - Gasto en innovación","right_id":6,"indicator_type_id":2,"indicator_category_id":2,"indicator_formule_code":"$$ PGPFCTI_t = \\left( \\frac{{GPFCTI}_{t}}{{GCTI_{t}}} \\right)*100 $$","indicator_calculation_element":"$* {PGPFCTI_{t}}:$*  Porcentaje del gasto público federal en ciencia, tecnología e innovación, respecto al gasto nacional en ciencia, tecnología e innovación (público, privado y de instituciones de educación superior).\n$* {GPFCTI_{t}}:$*  Gasto público federal en ciencia, tecnología e innovación, en el año t.\n$* {GCTI_{t}}:$* Gasto nacional en ciencia, tecnología e innovación, en el año t.\n$* {t}:$* Año de cálculo.","indicator_source_formule":"Fórmula descriptiva propuesta por el PUDH-UNAM","indicator_measure_unit":"Porcentaje","indicator_justification":null,"indicator_reference":"Indicador calculado por el Consejo Nacional de Ciencia y Tecnología (Conacyt)","indicator_observation":null,"indicator_comments":null,"responsible_institution":"Consejo Nacional de Ciencia y Tecnología (Conacyt)","lastmodified":"2018-06-20 14:00:09.581194","modified":"2018-02-20 00:00:00.0","type_collection":"Derechos Humanos","parent_cat_noun":"Indicadores, Programa Universitario de Derechos Humanos","data_category":"Registros","data_source":"indicator","data_descr":"Indicador","parent_category":"Acervos","identifier":"PUDH:INDI:CfP02"}